{
  "response_a": {
    "scores": {
      "clarity": 5,
      "correctness": 2,
      "responsibility": 1
    },
    "strengths": [
      "Very clear and concise statement.",
      "Shows empathy by apologizing."
    ],
    "weaknesses": [
      "Promises a refund without first verifying the claim, which is not responsible.",
      "Lacks request for necessary information to confirm the double charge.",
      "May lead to operational errors or abuse."
    ]
  },
  "response_b": {
    "scores": {
      "clarity": 5,
      "correctness": 5,
      "responsibility": 5
    },
    "strengths": [
      "Clear and polite tone.",
      "Requests necessary account details to verify the issue before taking action.",
      "Demonstrates responsible handling of refunds by ensuring verification."
    ],
    "weaknesses": [
      "Could be slightly more specific about expected response time."
    ]
  },
  "winner": "B",
  "judge_reasoning_summary": "Response B is clearer about next steps, correctly seeks verification before issuing a refund, and adheres to responsible refund handling practices. Response A, while clear, prematurely promises a refund without verification, violating responsible handling guidelines."
}